{"ActionScript":24391,"C":1726646,"C#":2893002,"C++":2569474,"Clojure":76537,"CoffeeScript":65200,"CSS":2039268,"Go":492428,"Haskell":90144,"HTML":5367639,"Java":9827505,"JavaScript":14240090,"Lua":176737,"MATLAB":261851,"Objective-C":520404,"Perl":164449,"PHP":2385827,"Python":6909587,"R":542409,"Ruby":1904129,"Scala":169841,"Shell":1259801,"Swift":858583,"TeX":181415,"Vim script":132584,"1C Enterprise":1860,"4D":232,"ABAP":3305,"ABNF":0,"Ada":4076,"Adobe Font Metrics":0,"Agda":1754,"AGS Script":2252,"Alloy":654,"Alpine Abuild":0,"Altium Designer":2,"AMPL":4094,"AngelScript":903,"Ant Build System":0,"ANTLR":1181,"ApacheConf":13256,"Apex":17530,"API Blueprint":2841,"APL":315,"Apollo Guidance Computer":0,"AppleScript":3181,"Arc":220,"AsciiDoc":2,"ASN.1":0,"ASP":50568,"AspectJ":678,"Assembly":86459,"Asymptote":63,"ATS":208,"Augeas":61,"AutoHotkey":11719,"AutoIt":4227,"Awk":2169,"Ballerina":1110,"Batchfile":54457,"Befunge":1,"BibTeX":0,"Bison":201,"BitBake":2803,"Blade":17833,"BlitzBasic":518,"BlitzMax":204,"Bluespec":222,"Boo":217,"Brainfuck":1282,"Brightscript":693,"C-ObjDump":0,"C2hs Haskell":0,"Cabal Config":0,"Cap'n Proto":93,"CartoCSS":422,"Ceylon":339,"Chapel":181,"Charity":9,"ChucK":512,"Cirru":287,"Clarion":187,"Clean":189,"Click":34,"CLIPS":1355,"Closure Templates":2,"Cloud Firestore Security Rules":0,"CMake":53325,"COBOL":2486,"CodeQL":2338,"ColdFusion":20392,"ColdFusion CFC":0,"COLLADA":0,"Common Lisp":22035,"Common Workflow Language":700,"Component Pascal":1215,"CoNLL-U":0,"Cool":82,"Coq":4628,"Cpp-ObjDump":0,"Creole":0,"Crystal":6682,"CSON":14,"Csound":47,"Csound Document":292,"Csound Score":48,"CSV":2,"Cuda":15158,"cURL Config":0,"CWeb":407,"Cycript":60,"Cython":0,"D":12382,"D-ObjDump":0,"Dafny":79,"Darcs Patch":0,"Dart":422007,"DataWeave":764,"desktop":0,"Dhall":576,"Diff":299,"DIGITAL Command Language":3700,"dircolors":0,"DirectX 3D File":0,"DM":1760,"DNS Zone":0,"Dockerfile":246277,"Dogescript":31,"DTrace":479,"Dylan":140,"E":348,"Eagle":9111,"Easybuild":0,"EBNF":0,"eC":111,"Ecere Projects":0,"ECL":185,"ECLiPSe":0,"EditorConfig":0,"Edje Data Collection":1,"edn":0,"Eiffel":921,"EJS":18012,"Elixir":75297,"Elm":18299,"Emacs Lisp":58068,"EmberScript":199,"EML":0,"EQ":23,"Erlang":27409,"F#":21794,"F*":195,"Factor":185,"Fancy":23,"Fantom":154,"Faust":129,"FIGlet Font":0,"Filebench WML":24,"Filterscript":0,"fish":0,"FLUX":174,"Formatted":0,"Forth":1290,"Fortran":24697,"Fortran Free Form":0,"FreeMarker":4994,"Frege":220,"Futhark":73,"G-code":2849,"Game Maker Language":6751,"GAML":222,"GAMS":651,"GAP":2752,"GCC Machine Description":1963,"GDB":799,"GDScript":25536,"GEDCOM":0,"Genie":17,"Genshi":26,"Gentoo Ebuild":0,"Gentoo Eclass":0,"Gerber Image":1,"Gettext Catalog":243,"Gherkin":5258,"Git Attributes":0,"Git Config":0,"GLSL":9419,"Glyph":91,"Glyph Bitmap Distribution Format":0,"GN":0,"Gnuplot":1951,"Golo":47,"Gosu":705,"Grace":27,"Gradle":3,"Grammatical Framework":162,"Graph Modeling Language":0,"GraphQL":0,"Graphviz (DOT)":326,"Groovy":65748,"Groovy Server Pages":0,"Hack":46414,"Haml":211,"Handlebars":11925,"HAProxy":0,"Harbour":49,"Haxe":11156,"HCL":102739,"HiveQL":279,"HLSL":1529,"HolyC":69,"HTML+Django":4416,"HTML+ECR":0,"HTML+EEX":0,"HTML+ERB":0,"HTML+PHP":0,"HTML+Razor":0,"HTTP":0,"HXML":0,"Hy":353,"HyPhy":110,"IDL":2277,"Idris":1601,"Ignore List":0,"IGOR Pro":372,"Inform 7":349,"INI":5,"Inno Setup":1028,"Io":1614,"Ioke":16,"IRC log":0,"Isabelle":679,"Isabelle ROOT":0,"J":408,"Jasmin":63,"Java Properties":0,"Java Server Pages":0,"JavaScript+ERB":0,"JFlex":2,"Jison":0,"Jison Lex":0,"Jolie":111,"JSON":52,"JSON with Comments":0,"JSON5":0,"JSONiq":162,"JSONLD":0,"Jsonnet":867,"JSX":54711718,"Julia":41522,"Jupyter Notebook":2239515,"KiCad Layout":4307,"KiCad Legacy Layout":0,"KiCad Schematic":7,"Kit":147,"Kotlin":556695,"KRL":381,"LabVIEW":4999,"Lasso":346,"Latte":118,"Lean":1169,"Less":6034,"Lex":2361,"LFE":45,"LilyPond":1746,"Limbo":471,"Linker Script":0,"Linux Kernel Module":0,"Liquid":6007,"Literate Agda":0,"Literate CoffeeScript":0,"Literate Haskell":0,"LiveScript":1863,"LLVM":1094,"Logos":6122,"Logtalk":46,"LOLCODE":182,"LookML":4695,"LoomScript":16,"LSL":545,"LTspice Symbol":0,"M":2250,"M4":2161,"M4Sugar":0,"Macaulay2":97,"Makefile":203938,"Mako":174,"Markdown":472,"Marko":47,"Mask":318,"Mathematica":17805,"Maven POM":0,"Max":5211,"MAXScript":1734,"mcfunction":2214,"MediaWiki":0,"Mercury":717,"Meson":661,"Metal":63,"Microsoft Developer Studio Project":0,"MiniD":0,"Mirah":67,"mIRC Script":114,"MLIR":52,"Modelica":856,"Modula-2":282,"Modula-3":116,"Module Management System":18,"Monkey":254,"Moocode":19,"MoonScript":748,"Motorola 68K Assembly":0,"MQL4":1003,"MQL5":1022,"MTML":81,"MUF":0,"mupad":35,"Muse":0,"Myghty":1,"nanorc":0,"NASL":122,"NCL":560,"Nearley":44,"Nemerle":175,"NEON":0,"nesC":1431,"NetLinx":121,"NetLinx+ERB":0,"NetLogo":3189,"NewLisp":426,"Nextflow":1976,"Nginx":6086,"Nim":6217,"Ninja":0,"Nit":28,"Nix":7857,"NL":0,"NPM Config":0,"NSIS":4583,"Nu":83,"NumPy":0,"ObjDump":0,"Object Data Instance Notation":0,"Objective-C++":4551,"Objective-J":972,"ObjectScript":695,"OCaml":24355,"Odin":150,"Omgrofl":3,"ooc":229,"Opa":78,"Opal":8,"Open Policy Agent":393,"OpenCL":0,"OpenEdge ABL":4413,"OpenQASM":81,"OpenRC runscript":0,"OpenSCAD":9334,"OpenStep Property List":0,"OpenType Feature File":0,"Org":11,"Ox":43,"Oxygene":67,"Oz":319,"P4":406,"Pan":24,"Papyrus":2362,"Parrot":91,"Parrot Assembly":0,"Parrot Internal Representation":0,"Pascal":40404,"Pawn":2451,"Pep8":125,"Pic":0,"Pickle":0,"PicoLisp":97,"PigLatin":1199,"Pike":140,"PlantUML":1,"PLpgSQL":19776,"PLSQL":17709,"Pod":0,"Pod 6":0,"PogoScript":50,"Pony":471,"PostCSS":0,"PostScript":7160,"POV-Ray SDL":696,"PowerBuilder":736,"PowerShell":133649,"Prisma":0,"Processing":68609,"Proguard":0,"Prolog":19092,"Propeller Spin":429,"Protocol Buffer":1157,"Public Key":1,"Pug":5120,"Puppet":23129,"Pure Data":1602,"PureBasic":2598,"PureScript":4917,"Python console":0,"Python traceback":0,"q":627,"QMake":3504,"QML":12329,"Quake":1,"Racket":15633,"Ragel":57,"Raku":1772,"RAML":3171,"Rascal":604,"Raw token data":0,"RDoc":0,"Readline Config":0,"REALbasic":99,"Reason":1751,"Rebol":27420,"Red":408,"Redcode":30,"Regular Expression":0,"Ren'Py":2209,"RenderScript":662,"reStructuredText":23,"REXX":186,"RHTML":0,"Rich Text Format":16465,"Ring":178,"Riot":108,"RMarkdown":54,"RobotFramework":4905,"Roff":27986,"Roff Manpage":0,"Rouge":68,"RPC":753,"RPM Spec":0,"RUNOFF":4,"Rust":224289,"Sage":230,"SaltStack":4235,"SAS":7195,"Sass":5229,"Scaml":0,"Scheme":15392,"Scilab":3357,"SCSS":141047,"sed":263,"Self":32,"ShaderLab":30203,"ShellSession":0,"Shen":45,"Sieve":8,"Slash":526,"Slice":36,"Slim":174,"Smali":2084,"Smalltalk":7273,"Smarty":23946,"SmPL":14,"SMT":458,"Solidity":19354,"SourcePawn":5902,"SPARQL":0,"Spline Font Database":0,"SQF":5462,"SQL":720,"SQLPL":7906,"Squirrel":1182,"SRecode Template":168,"SSH Config":0,"Stan":590,"Standard ML":4662,"Starlark":1820,"Stata":6249,"STON":0,"Stylus":3612,"SubRip Text":0,"SugarSS":0,"SuperCollider":3297,"Svelte":8373,"SVG":4,"SWIG":1718,"SystemVerilog":7046,"Tcl":11781,"Tcsh":0,"Tea":7,"Terra":348,"Texinfo":1,"Text":16,"Textile":0,"Thrift":367,"TI Program":52,"TLA":525,"TOML":0,"TSQL":66462,"TSX":0,"Turing":481,"Turtle":3,"Twig":2675,"TXL":56,"Type Language":0,"TypeScript":1986262,"Unified Parallel C":0,"Unity3D Asset":0,"Unix Assembly":0,"Uno":224,"UnrealScript":1132,"UrWeb":78,"V":731,"Vala":3182,"VBA":22768,"VBScript":3538,"VCL":529,"Verilog":35427,"VHDL":27874,"Vim Snippet":1177,"Visual Basic .NET":73642,"Volt":151,"Vue":578153,"Wavefront Material":0,"Wavefront Object":0,"wdl":588,"Web Ontology Language":1873,"WebAssembly":1302,"WebIDL":16,"WebVTT":0,"Wget Config":0,"Windows Registry Entries":3,"wisp":29,"Wollok":1553,"World of Warcraft Addon Data":0,"X BitMap":0,"X Font Directory Index":0,"X PixMap":0,"X10":44,"xBase":2084,"XC":339,"XCompose":0,"XML":3325,"XML Property List":0,"Xojo":457,"XPages":22,"XProc":86,"XQuery":1641,"XS":473,"XSLT":23420,"Xtend":1407,"Yacc":7567,"YAML":211,"YANG":0,"YARA":438,"YASnippet":310,"ZAP":56,"Zeek":1042,"ZenScript":978,"Zephir":90,"Zig":1574,"ZIL":170,"Zimpl":45}